{
  "data": [
    {
      "id": 13930839,
      "ast": 4,
      "blk": 1,
      "dreb": 1,
      "fg3_pct": 0.25,
      "fg3a": 4,
      "fg3m": 1,
      "fg_pct": 0.458,
      "fga": 24,
      "fgm": 11,
      "ft_pct": 0.833,
      "fta": 6,
      "ftm": 5,
      "game": {
        "id": 1011167,
        "date": "2023-06-07T00:00:00.000Z",
        "home_team_id": 16,
        "home_team_score": 94,
        "period": 4,
        "postseason": true,
        "season": 2022,
        "status": "Final",
        "time": "Final",
        "visitor_team_id": 8,
        "visitor_team_score": 109
      },
      "min": "40",
      "oreb": 1,
      "pf": 2,
      "player": {
        "id": 79,
        "first_name": "Jimmy",
        "height_feet": 6,
        "height_inches": 8,
        "last_name": "Butler",
        "position": "G-F",
        "team_id": 16,
        "weight_pounds": 232
      },
      "pts": 28,
      "reb": 2,
      "stl": 0,
      "team": {
        "id": 16,
        "abbreviation": "MIA",
        "city": "Miami",
        "conference": "East",
        "division": "Southeast",
        "full_name": "Miami Heat",
        "name": "Heat"
      },
      "turnover": 2
    },
    {
      "id": 13930840,
      "ast": 0,
      "blk": 0,
      "dreb": 2,
      "fg3_pct": 0.4,
      "fg3a": 5,
      "fg3m": 2,
      "fg_pct": 0.4,
      "fga": 5,
      "fgm": 2,
      "ft_pct": 0.0,
      "fta": 0,
      "ftm": 0,
      "game": {
        "id": 1011167,
        "date": "2023-06-07T00:00:00.000Z",
        "home_team_id": 16,
        "home_team_score": 94,
        "period": 4,
        "postseason": true,
        "season": 2022,
        "status": "Final",
        "time": "Final",
        "visitor_team_id": 8,
        "visitor_team_score": 109
      },
      "min": "16",
      "oreb": 0,
      "pf": 2,
      "player": {
        "id": 285,
        "first_name": "Kevin",
        "height_feet": 6,
        "height_inches": 10,
        "last_name": "Love",
        "position": "F-C",
        "team_id": 16,
        "weight_pounds": 251
      },
      "pts": 6,
      "reb": 2,
      "stl": 0,
      "team": {
        "id": 16,
        "abbreviation": "MIA",
        "city": "Miami",
        "conference": "East",
        "division": "Southeast",
        "full_name": "Miami Heat",
        "name": "Heat"
      },
      "turnover": 0
    },
    {
      "id": 13930841,
      "ast": 3,
      "blk": 1,
      "dreb": 11,
      "fg3_pct": null,
      "fg3a": 0,
      "fg3m": 0,
      "fg_pct": 0.333,
      "fga": 21,
      "fgm": 7,
      "ft_pct": 0.8,
      "fta": 10,
      "ftm": 8,
      "game": {
        "id": 1011167,
        "date": "2023-06-07T00:00:00.000Z",
        "home_team_id": 16,
        "home_team_score": 94,
        "period": 4,
        "postseason": true,
        "season": 2022,
        "status": "Final",
        "time": "Final",
        "visitor_team_id": 8,
        "visitor_team_score": 109
      },
      "min": "41",
      "oreb": 6,
      "pf": 2,
      "player": {
        "id": 4,
        "first_name": "Bam",
        "height_feet": 6,
        "height_inches": 10,
        "last_name": "Adebayo",
        "position": "C-F",
        "team_id": 16,
        "weight_pounds": 255
      },
      "pts": 22,
      "reb": 17,
      "stl": 0,
      "team": {
        "id": 16,
        "abbreviation": "MIA",
        "city": "Miami",
        "conference": "East",
        "division": "Southeast",
        "full_name": "Miami Heat",
        "name": "Heat"
      },
      "turnover": 0
    },
    {
      "id": 13930842,
      "ast": 5,
      "blk": 1,
      "dreb": 2,
      "fg3_pct": 0.25,
      "fg3a": 4,
      "fg3m": 1,
      "fg_pct": 0.14285715,
      "fga": 7,
      "fgm": 1,
      "ft_pct": 0.0,
      "fta": 0,
      "ftm": 0,
      "game": {
        "id": 1011167,
        "date": "2023-06-07T00:00:00.000Z",
        "home_team_id": 16,
        "home_team_score": 94,
        "period": 4,
        "postseason": true,
        "season": 2022,
        "status": "Final",
        "time": "Final",
        "visitor_team_id": 8,
        "visitor_team_score": 109
      },
      "min": "24",
      "oreb": 2,
      "pf": 1,
      "player": {
        "id": 666908,
        "first_name": "Max",
        "height_feet": null,
        "height_inches": null,
        "last_name": "Strus",
        "position": "G",
        "team_id": 16,
        "weight_pounds": null
      },
      "pts": 3,
      "reb": 4,
      "stl": 1,
      "team": {
        "id": 16,
        "abbreviation": "MIA",
        "city": "Miami",
        "conference": "East",
        "division": "Southeast",
        "full_name": "Miami Heat",
        "name": "Heat"
      },
      "turnover": 0
    },
    {
      "id": 13930843,
      "ast": 0,
      "blk": 0,
      "dreb": 0,
      "fg3_pct": 0.167,
      "fg3a": 6,
      "fg3m": 1,
      "fg_pct": 0.2,
      "fga": 10,
      "fgm": 2,
      "ft_pct": 0.667,
      "fta": 3,
      "ftm": 2,
      "game": {
        "id": 1011167,
        "date": "2023-06-07T00:00:00.000Z",
        "home_team_id": 16,
        "home_team_score": 94,
        "period": 4,
        "postseason": true,
        "season": 2022,
        "status": "Final",
        "time": "Final",
        "visitor_team_id": 8,
        "visitor_team_score": 109
      },
      "min": "32",
      "oreb": 0,
      "pf": 3,
      "player": {
        "id": 1603383,
        "first_name": "Gabe",
        "height_feet": null,
        "height_inches": null,
        "last_name": "Vincent",
        "position": "G",
        "team_id": 16,
        "weight_pounds": null
      },
      "pts": 7,
      "reb": 0,
      "stl": 2,
      "team": {
        "id": 16,
        "abbreviation": "MIA",
        "city": "Miami",
        "conference": "East",
        "division": "Southeast",
        "full_name": "Miami Heat",
        "name": "Heat"
      },
      "turnover": 0
    },
    {
      "id": 13930844,
      "ast": 0,
      "blk": 0,
      "dreb": 0,
      "fg3_pct": 0.0,
      "fg3a": 0,
      "fg3m": 0,
      "fg_pct": 0.0,
      "fga": 1,
      "fgm": 0,
      "ft_pct": 0.0,
      "fta": 0,
      "ftm": 0,
      "game": {
        "id": 1011167,
        "date": "2023-06-07T00:00:00.000Z",
        "home_team_id": 16,
        "home_team_score": 94,
        "period": 4,
        "postseason": true,
        "season": 2022,
        "status": "Final",
        "time": "Final",
        "visitor_team_id": 8,
        "visitor_team_score": 109
      },
      "min": "01",
      "oreb": 0,
      "pf": 0,
      "player": {
        "id": 203,
        "first_name": "Udonis",
        "height_feet": 6,
        "height_inches": 8,
        "last_name": "Haslem",
        "position": "F",
        "team_id": 16,
        "weight_pounds": 235
      },
      "pts": 0,
      "reb": 0,
      "stl": 0,
      "team": {
        "id": 16,
        "abbreviation": "MIA",
        "city": "Miami",
        "conference": "East",
        "division": "Southeast",
        "full_name": "Miami Heat",
        "name": "Heat"
      },
      "turnover": 0
    },
    {
      "id": 13930845,
      "ast": 0,
      "blk": 0,
      "dreb": 0,
      "fg3_pct": 0.0,
      "fg3a": 0,
      "fg3m": 0,
      "fg_pct": 0.0,
      "fga": 0,
      "fgm": 0,
      "ft_pct": 0.0,
      "fta": 0,
      "ftm": 0,
      "game": {
        "id": 1011167,
        "date": "2023-06-07T00:00:00.000Z",
        "home_team_id": 16,
        "home_team_score": 94,
        "period": 4,
        "postseason": true,
        "season": 2022,
        "status": "Final",
        "time": "Final",
        "visitor_team_id": 8,
        "visitor_team_score": 109
      },
      "min": "02",
      "oreb": 0,
      "pf": 1,
      "player": {
        "id": 3092,
        "first_name": "Haywood",
        "height_feet": 6,
        "height_inches": 7,
        "last_name": "Highsmith",
        "position": "",
        "team_id": 16,
        "weight_pounds": 220
      },
      "pts": 0,
      "reb": 0,
      "stl": 0,
      "team": {
        "id": 16,
        "abbreviation": "MIA",
        "city": "Miami",
        "conference": "East",
        "division": "Southeast",
        "full_name": "Miami Heat",
        "name": "Heat"
      },
      "turnover": 0
    },
    {
      "id": 13930846,
      "ast": 0,
      "blk": 0,
      "dreb": 0,
      "fg3_pct": 0.0,
      "fg3a": 0,
      "fg3m": 0,
      "fg_pct": 0.0,
      "fga": 0,
      "fgm": 0,
      "ft_pct": 0.0,
      "fta": 0,
      "ftm": 0,
      "game": {
        "id": 1011167,
        "date": "2023-06-07T00:00:00.000Z",
        "home_team_id": 16,
        "home_team_score": 94,
        "period": 4,
        "postseason": true,
        "season": 2022,
        "status": "Final",
        "time": "Final",
        "visitor_team_id": 8,
        "visitor_team_score": 109
      },
      "min": "02",
      "oreb": 0,
      "pf": 0,
      "player": {
        "id": 38017696,
        "first_name": "Nikola",
        "height_feet": null,
        "height_inches": null,
        "last_name": "Jovic",
        "position": "F",
        "team_id": 16,
        "weight_pounds": null
      },
      "pts": 0,
      "reb": 0,
      "stl": 0,
      "team": {
        "id": 16,
        "abbreviation": "MIA",
        "city": "Miami",
        "conference": "East",
        "division": "Southeast",
        "full_name": "Miami Heat",
        "name": "Heat"
      },
      "turnover": 0
    },
    {
      "id": 13930847,
      "ast": 5,
      "blk": 0,
      "dreb": 3,
      "fg3_pct": 0.25,
      "fg3a": 4,
      "fg3m": 1,
      "fg_pct": 0.5,
      "fga": 8,
      "fgm": 4,
      "ft_pct": 0.0,
      "fta": 0,
      "ftm": 0,
      "game": {
        "id": 1011167,
        "date": "2023-06-07T00:00:00.000Z",
        "home_team_id": 16,
        "home_team_score": 94,
        "period": 4,
        "postseason": true,
        "season": 2022,
        "status": "Final",
        "time": "Final",
        "visitor_team_id": 8,
        "visitor_team_score": 109
      },
      "min": "29",
      "oreb": 0,
      "pf": 4,
      "player": {
        "id": 286,
        "first_name": "Kyle",
        "height_feet": 6,
        "height_inches": 1,
        "last_name": "Lowry",
        "position": "G",
        "team_id": 16,
        "weight_pounds": 196
      },
      "pts": 9,
      "reb": 3,
      "stl": 2,
      "team": {
        "id": 16,
        "abbreviation": "MIA",
        "city": "Miami",
        "conference": "East",
        "division": "Southeast",
        "full_name": "Miami Heat",
        "name": "Heat"
      },
      "turnover": 1
    },
    {
      "id": 13930848,
      "ast": 3,
      "blk": 0,
      "dreb": 3,
      "fg3_pct": 0.4,
      "fg3a": 5,
      "fg3m": 2,
      "fg_pct": 0.444,
      "fga": 9,
      "fgm": 4,
      "ft_pct": null,
      "fta": 0,
      "ftm": 0,
      "game": {
        "id": 1011167,
        "date": "2023-06-07T00:00:00.000Z",
        "home_team_id": 16,
        "home_team_score": 94,
        "period": 4,
        "postseason": true,
        "season": 2022,
        "status": "Final",
        "time": "Final",
        "visitor_team_id": 8,
        "visitor_team_score": 109
      },
      "min": "32",
      "oreb": 0,
      "pf": 4,
      "player": {
        "id": 666747,
        "first_name": "Caleb",
        "height_feet": null,
        "height_inches": null,
        "last_name": "Martin",
        "position": "F",
        "team_id": 16,
        "weight_pounds": null
      },
      "pts": 10,
      "reb": 3,
      "stl": 2,
      "team": {
        "id": 16,
        "abbreviation": "MIA",
        "city": "Miami",
        "conference": "East",
        "division": "Southeast",
        "full_name": "Miami Heat",
        "name": "Heat"
      },
      "turnover": 1
    },
    {
      "id": 13930849,
      "ast": 0,
      "blk": 0,
      "dreb": 1,
      "fg3_pct": 0.5,
      "fg3a": 6,
      "fg3m": 3,
      "fg_pct": 0.5,
      "fga": 6,
      "fgm": 3,
      "ft_pct": null,
      "fta": 0,
      "ftm": 0,
      "game": {
        "id": 1011167,
        "date": "2023-06-07T00:00:00.000Z",
        "home_team_id": 16,
        "home_team_score": 94,
        "period": 4,
        "postseason": true,
        "season": 2022,
        "status": "Final",
        "time": "Final",
        "visitor_team_id": 8,
        "visitor_team_score": 109
      },
      "min": "14",
      "oreb": 0,
      "pf": 2,
      "player": {
        "id": 397,
        "first_name": "Duncan",
        "height_feet": 6,
        "height_inches": 8,
        "last_name": "Robinson",
        "position": "F",
        "team_id": 16,
        "weight_pounds": 210
      },
      "pts": 9,
      "reb": 1,
      "stl": 0,
      "team": {
        "id": 16,
        "abbreviation": "MIA",
        "city": "Miami",
        "conference": "East",
        "division": "Southeast",
        "full_name": "Miami Heat",
        "name": "Heat"
      },
      "turnover": 0
    },
    {
      "id": 13930850,
      "ast": 0,
      "blk": 0,
      "dreb": 0,
      "fg3_pct": 0.0,
      "fg3a": 1,
      "fg3m": 0,
      "fg_pct": 0.0,
      "fga": 1,
      "fgm": 0,
      "ft_pct": 0.0,
      "fta": 0,
      "ftm": 0,
      "game": {
        "id": 1011167,
        "date": "2023-06-07T00:00:00.000Z",
        "home_team_id": 16,
        "home_team_score": 94,
        "period": 4,
        "postseason": true,
        "season": 2022,
        "status": "Final",
        "time": "Final",
        "visitor_team_id": 8,
        "visitor_team_score": 109
      },
      "min": "01",
      "oreb": 1,
      "pf": 0,
      "player": {
        "id": 11891374,
        "first_name": "Omer",
        "height_feet": null,
        "height_inches": null,
        "last_name": "Yurtseven",
        "position": "C",
        "team_id": 16,
        "weight_pounds": null
      },
      "pts": 0,
      "reb": 1,
      "stl": 0,
      "team": {
        "id": 16,
        "abbreviation": "MIA",
        "city": "Miami",
        "conference": "East",
        "division": "Southeast",
        "full_name": "Miami Heat",
        "name": "Heat"
      },
      "turnover": 0
    },
    {
      "id": 13930851,
      "ast": 0,
      "blk": 0,
      "dreb": 0,
      "fg3_pct": 0.0,
      "fg3a": 0,
      "fg3m": 0,
      "fg_pct": 0.0,
      "fga": 0,
      "fgm": 0,
      "ft_pct": 0.0,
      "fta": 0,
      "ftm": 0,
      "game": {
        "id": 1011167,
        "date": "2023-06-07T00:00:00.000Z",
        "home_team_id": 16,
        "home_team_score": 94,
        "period": 4,
        "postseason": true,
        "season": 2022,
        "status": "Final",
        "time": "Final",
        "visitor_team_id": 8,
        "visitor_team_score": 109
      },
      "min": "06",
      "oreb": 0,
      "pf": 1,
      "player": {
        "id": 491,
        "first_name": "Cody",
        "height_feet": 7,
        "height_inches": 0,
        "last_name": "Zeller",
        "position": "C",
        "team_id": 16,
        "weight_pounds": 240
      },
      "pts": 0,
      "reb": 0,
      "stl": 0,
      "team": {
        "id": 16,
        "abbreviation": "MIA",
        "city": "Miami",
        "conference": "East",
        "division": "Southeast",
        "full_name": "Miami Heat",
        "name": "Heat"
      },
      "turnover": 0
    },
    {
      "id": 13930852,
      "ast": 0,
      "blk": 0,
      "dreb": 0,
      "fg3_pct": 0.0,
      "fg3a": 0,
      "fg3m": 0,
      "fg_pct": 0.0,
      "fga": 0,
      "fgm": 0,
      "ft_pct": 0.0,
      "fta": 0,
      "ftm": 0,
      "game": {
        "id": 1011167,
        "date": "2023-06-07T00:00:00.000Z",
        "home_team_id": 16,
        "home_team_score": 94,
        "period": 4,
        "postseason": true,
        "season": 2022,
        "status": "Final",
        "time": "Final",
        "visitor_team_id": 8,
        "visitor_team_score": 109
      },
      "min": "00",
      "oreb": 0,
      "pf": 0,
      "player": {
        "id": 666633,
        "first_name": "Tyler",
        "height_feet": null,
        "height_inches": null,
        "last_name": "Herro",
        "position": "G",
        "team_id": 16,
        "weight_pounds": null
      },
      "pts": 0,
      "reb": 0,
      "stl": 0,
      "team": {
        "id": 16,
        "abbreviation": "MIA",
        "city": "Miami",
        "conference": "East",
        "division": "Southeast",
        "full_name": "Miami Heat",
        "name": "Heat"
      },
      "turnover": 0
    },
    {
      "id": 13930858,
      "ast": 10,
      "blk": 0,
      "dreb": 7,
      "fg3_pct": 0.5,
      "fg3a": 6,
      "fg3m": 3,
      "fg_pct": 0.545,
      "fga": 22,
      "fgm": 12,
      "ft_pct": 0.875,
      "fta": 8,
      "ftm": 7,
      "game": {
        "id": 1011167,
        "date": "2023-06-07T00:00:00.000Z",
        "home_team_id": 16,
        "home_team_score": 94,
        "period": 4,
        "postseason": true,
        "season": 2022,
        "status": "Final",
        "time": "Final",
        "visitor_team_id": 8,
        "visitor_team_score": 109
      },
      "min": "45",
      "oreb": 3,
      "pf": 2,
      "player": {
        "id": 335,
        "first_name": "Jamal",
        "height_feet": 6,
        "height_inches": 4,
        "last_name": "Murray",
        "position": "G",
        "team_id": 8,
        "weight_pounds": 207
      },
      "pts": 34,
      "reb": 10,
      "stl": 1,
      "team": {
        "id": 8,
        "abbreviation": "DEN",
        "city": "Denver",
        "conference": "West",
        "division": "Northwest",
        "full_name": "Denver Nuggets",
        "name": "Nuggets"
      },
      "turnover": 7
    },
    {
      "id": 13930859,
      "ast": 1,
      "blk": 0,
      "dreb": 2,
      "fg3_pct": 0.0,
      "fg3a": 1,
      "fg3m": 0,
      "fg_pct": 0.875,
      "fga": 8,
      "fgm": 7,
      "ft_pct": 1.0,
      "fta": 1,
      "ftm": 1,
      "game": {
        "id": 1011167,
        "date": "2023-06-07T00:00:00.000Z",
        "home_team_id": 16,
        "home_team_score": 94,
        "period": 4,
        "postseason": true,
        "season": 2022,
        "status": "Final",
        "time": "Final",
        "visitor_team_id": 8,
        "visitor_team_score": 109
      },
      "min": "19",
      "oreb": 2,
      "pf": 1,
      "player": {
        "id": 38017709,
        "first_name": "Christian",
        "height_feet": null,
        "height_inches": null,
        "last_name": "Braun",
        "position": "G",
        "team_id": 8,
        "weight_pounds": null
      },
      "pts": 15,
      "reb": 4,
      "stl": 1,
      "team": {
        "id": 8,
        "abbreviation": "DEN",
        "city": "Denver",
        "conference": "West",
        "division": "Northwest",
        "full_name": "Denver Nuggets",
        "name": "Nuggets"
      },
      "turnover": 1
    },
    {
      "id": 13930860,
      "ast": 0,
      "blk": 3,
      "dreb": 2,
      "fg3_pct": 0.33333334,
      "fg3a": 3,
      "fg3m": 1,
      "fg_pct": 0.2,
      "fga": 5,
      "fgm": 1,
      "ft_pct": 1.0,
      "fta": 2,
      "ftm": 2,
      "game": {
        "id": 1011167,
        "date": "2023-06-07T00:00:00.000Z",
        "home_team_id": 16,
        "home_team_score": 94,
        "period": 4,
        "postseason": true,
        "season": 2022,
        "status": "Final",
        "time": "Final",
        "visitor_team_id": 8,
        "visitor_team_score": 109
      },
      "min": "28",
      "oreb": 0,
      "pf": 3,
      "player": {
        "id": 69,
        "first_name": "Bruce",
        "height_feet": 6,
        "height_inches": 5,
        "last_name": "Brown",
        "position": "G",
        "team_id": 8,
        "weight_pounds": 202
      },
      "pts": 5,
      "reb": 2,
      "stl": 0,
      "team": {
        "id": 8,
        "abbreviation": "DEN",
        "city": "Denver",
        "conference": "West",
        "division": "Northwest",
        "full_name": "Denver Nuggets",
        "name": "Nuggets"
      },
      "turnover": 1
    },
    {
      "id": 13930854,
      "ast": 0,
      "blk": 0,
      "dreb": 5,
      "fg3_pct": 0.0,
      "fg3a": 2,
      "fg3m": 0,
      "fg_pct": 0.14285715,
      "fga": 7,
      "fgm": 1,
      "ft_pct": 0.0,
      "fta": 0,
      "ftm": 0,
      "game": {
        "id": 1011167,
        "date": "2023-06-07T00:00:00.000Z",
        "home_team_id": 16,
        "home_team_score": 94,
        "period": 4,
        "postseason": true,
        "season": 2022,
        "status": "Final",
        "time": "Final",
        "visitor_team_id": 8,
        "visitor_team_score": 109
      },
      "min": "21",
      "oreb": 2,
      "pf": 1,
      "player": {
        "id": 375,
        "first_name": "Michael",
        "height_feet": 6,
        "height_inches": 10,
        "last_name": "Porter Jr.",
        "position": "F",
        "team_id": 8,
        "weight_pounds": 210
      },
      "pts": 2,
      "reb": 7,
      "stl": 0,
      "team": {
        "id": 8,
        "abbreviation": "DEN",
        "city": "Denver",
        "conference": "West",
        "division": "Northwest",
        "full_name": "Denver Nuggets",
        "name": "Nuggets"
      },
      "turnover": 0
    },
    {
      "id": 13930855,
      "ast": 5,
      "blk": 0,
      "dreb": 7,
      "fg3_pct": null,
      "fg3a": 0,
      "fg3m": 0,
      "fg_pct": 0.5,
      "fga": 10,
      "fgm": 5,
      "ft_pct": 0.25,
      "fta": 4,
      "ftm": 1,
      "game": {
        "id": 1011167,
        "date": "2023-06-07T00:00:00.000Z",
        "home_team_id": 16,
        "home_team_score": 94,
        "period": 4,
        "postseason": true,
        "season": 2022,
        "status": "Final",
        "time": "Final",
        "visitor_team_id": 8,
        "visitor_team_score": 109
      },
      "min": "34",
      "oreb": 3,
      "pf": 3,
      "player": {
        "id": 177,
        "first_name": "Aaron",
        "height_feet": 6,
        "height_inches": 9,
        "last_name": "Gordon",
        "position": "F",
        "team_id": 8,
        "weight_pounds": 220
      },
      "pts": 11,
      "reb": 10,
      "stl": 1,
      "team": {
        "id": 8,
        "abbreviation": "DEN",
        "city": "Denver",
        "conference": "West",
        "division": "Northwest",
        "full_name": "Denver Nuggets",
        "name": "Nuggets"
      },
      "turnover": 0
    },
    {
      "id": 13930856,
      "ast": 10,
      "blk": 2,
      "dreb": 18,
      "fg3_pct": 0.5,
      "fg3a": 2,
      "fg3m": 1,
      "fg_pct": 0.571,
      "fga": 21,
      "fgm": 12,
      "ft_pct": 0.875,
      "fta": 8,
      "ftm": 7,
      "game": {
        "id": 1011167,
        "date": "2023-06-07T00:00:00.000Z",
        "home_team_id": 16,
        "home_team_score": 94,
        "period": 4,
        "postseason": true,
        "season": 2022,
        "status": "Final",
        "time": "Final",
        "visitor_team_id": 8,
        "visitor_team_score": 109
      },
      "min": "44",
      "oreb": 3,
      "pf": 5,
      "player": {
        "id": 246,
        "first_name": "Nikola",
        "height_feet": 7,
        "height_inches": 0,
        "last_name": "Jokic",
        "position": "C",
        "team_id": 8,
        "weight_pounds": 250
      },
      "pts": 32,
      "reb": 21,
      "stl": 0,
      "team": {
        "id": 8,
        "abbreviation": "DEN",
        "city": "Denver",
        "conference": "West",
        "division": "Northwest",
        "full_name": "Denver Nuggets",
        "name": "Nuggets"
      },
      "turnover": 3
    },
    {
      "id": 13930857,
      "ast": 0,
      "blk": 0,
      "dreb": 3,
      "fg3_pct": 0.0,
      "fg3a": 3,
      "fg3m": 0,
      "fg_pct": 0.25,
      "fga": 4,
      "fgm": 1,
      "ft_pct": 1.0,
      "fta": 4,
      "ftm": 4,
      "game": {
        "id": 1011167,
        "date": "2023-06-07T00:00:00.000Z",
        "home_team_id": 16,
        "home_team_score": 94,
        "period": 4,
        "postseason": true,
        "season": 2022,
        "status": "Final",
        "time": "Final",
        "visitor_team_id": 8,
        "visitor_team_score": 109
      },
      "min": "28",
      "oreb": 0,
      "pf": 2,
      "player": {
        "id": 81,
        "first_name": "Kentavious",
        "height_feet": 6,
        "height_inches": 5,
        "last_name": "Caldwell-Pope",
        "position": "G",
        "team_id": 8,
        "weight_pounds": 205
      },
      "pts": 6,
      "reb": 3,
      "stl": 0,
      "team": {
        "id": 8,
        "abbreviation": "DEN",
        "city": "Denver",
        "conference": "West",
        "division": "Northwest",
        "full_name": "Denver Nuggets",
        "name": "Nuggets"
      },
      "turnover": 1
    },
    {
      "id": 13930865,
      "ast": 0,
      "blk": 0,
      "dreb": 0,
      "fg3_pct": 0.0,
      "fg3a": 0,
      "fg3m": 0,
      "fg_pct": 0.0,
      "fga": 0,
      "fgm": 0,
      "ft_pct": 0.0,
      "fta": 0,
      "ftm": 0,
      "game": {
        "id": 1011167,
        "date": "2023-06-07T00:00:00.000Z",
        "home_team_id": 16,
        "home_team_score": 94,
        "period": 4,
        "postseason": true,
        "season": 2022,
        "status": "Final",
        "time": "Final",
        "visitor_team_id": 8,
        "visitor_team_score": 109
      },
      "min": "00",
      "oreb": 0,
      "pf": 0,
      "player": {
        "id": 250,
        "first_name": "DeAndre",
        "height_feet": 6,
        "height_inches": 11,
        "last_name": "Jordan",
        "position": "C",
        "team_id": 8,
        "weight_pounds": 265
      },
      "pts": 0,
      "reb": 0,
      "stl": 0,
      "team": {
        "id": 8,
        "abbreviation": "DEN",
        "city": "Denver",
        "conference": "West",
        "division": "Northwest",
        "full_name": "Denver Nuggets",
        "name": "Nuggets"
      },
      "turnover": 0
    },
    {
      "id": 13930866,
      "ast": 0,
      "blk": 0,
      "dreb": 0,
      "fg3_pct": 0.0,
      "fg3a": 0,
      "fg3m": 0,
      "fg_pct": 0.0,
      "fga": 0,
      "fgm": 0,
      "ft_pct": 0.0,
      "fta": 0,
      "ftm": 0,
      "game": {
        "id": 1011167,
        "date": "2023-06-07T00:00:00.000Z",
        "home_team_id": 16,
        "home_team_score": 94,
        "period": 4,
        "postseason": true,
        "season": 2022,
        "status": "Final",
        "time": "Final",
        "visitor_team_id": 8,
        "visitor_team_score": 109
      },
      "min": "01",
      "oreb": 0,
      "pf": 0,
      "player": {
        "id": 3547268,
        "first_name": "Zeke",
        "height_feet": null,
        "height_inches": null,
        "last_name": "Nnaji",
        "position": "F-C",
        "team_id": 8,
        "weight_pounds": null
      },
      "pts": 0,
      "reb": 0,
      "stl": 0,
      "team": {
        "id": 8,
        "abbreviation": "DEN",
        "city": "Denver",
        "conference": "West",
        "division": "Northwest",
        "full_name": "Denver Nuggets",
        "name": "Nuggets"
      },
      "turnover": 0
    },
    {
      "id": 13930867,
      "ast": 0,
      "blk": 0,
      "dreb": 0,
      "fg3_pct": 0.0,
      "fg3a": 0,
      "fg3m": 0,
      "fg_pct": 0.0,
      "fga": 0,
      "fgm": 0,
      "ft_pct": 0.0,
      "fta": 0,
      "ftm": 0,
      "game": {
        "id": 1011167,
        "date": "2023-06-07T00:00:00.000Z",
        "home_team_id": 16,
        "home_team_score": 94,
        "period": 4,
        "postseason": true,
        "season": 2022,
        "status": "Final",
        "time": "Final",
        "visitor_team_id": 8,
        "visitor_team_score": 109
      },
      "min": "00",
      "oreb": 0,
      "pf": 0,
      "player": {
        "id": 422,
        "first_name": "Ish",
        "height_feet": 6,
        "height_inches": 0,
        "last_name": "Smith",
        "position": "G",
        "team_id": 8,
        "weight_pounds": 175
      },
      "pts": 0,
      "reb": 0,
      "stl": 0,
      "team": {
        "id": 8,
        "abbreviation": "DEN",
        "city": "Denver",
        "conference": "West",
        "division": "Northwest",
        "full_name": "Denver Nuggets",
        "name": "Nuggets"
      },
      "turnover": 0
    },
    {
      "id": 13930868,
      "ast": 0,
      "blk": 0,
      "dreb": 0,
      "fg3_pct": 0.0,
      "fg3a": 0,
      "fg3m": 0,
      "fg_pct": 0.0,
      "fga": 0,
      "fgm": 0,
      "ft_pct": 0.0,
      "fta": 0,
      "ftm": 0,
      "game": {
        "id": 1011167,
        "date": "2023-06-07T00:00:00.000Z",
        "home_team_id": 16,
        "home_team_score": 94,
        "period": 4,
        "postseason": true,
        "season": 2022,
        "status": "Final",
        "time": "Final",
        "visitor_team_id": 8,
        "visitor_team_score": 109
      },
      "min": "01",
      "oreb": 0,
      "pf": 0,
      "player": {
        "id": 38017721,
        "first_name": "Peyton",
        "height_feet": null,
        "height_inches": null,
        "last_name": "Watson",
        "position": "G",
        "team_id": 8,
        "weight_pounds": null
      },
      "pts": 0,
      "reb": 0,
      "stl": 0,
      "team": {
        "id": 8,
        "abbreviation": "DEN",
        "city": "Denver",
        "conference": "West",
        "division": "Northwest",
        "full_name": "Denver Nuggets",
        "name": "Nuggets"
      },
      "turnover": 0
    },
    {
      "id": 13930853,
      "ast": 0,
      "blk": 0,
      "dreb": 0,
      "fg3_pct": 0.0,
      "fg3a": 0,
      "fg3m": 0,
      "fg_pct": 0.0,
      "fga": 0,
      "fgm": 0,
      "ft_pct": 0.0,
      "fta": 0,
      "ftm": 0,
      "game": {
        "id": 1011167,
        "date": "2023-06-07T00:00:00.000Z",
        "home_team_id": 16,
        "home_team_score": 94,
        "period": 4,
        "postseason": true,
        "season": 2022,
        "status": "Final",
        "time": "Final",
        "visitor_team_id": 8,
        "visitor_team_score": 109
      },
      "min": "00",
      "oreb": 0,
      "pf": 0,
      "player": {
        "id": 357,
        "first_name": "Victor",
        "height_feet": 6,
        "height_inches": 4,
        "last_name": "Oladipo",
        "position": "G",
        "team_id": 16,
        "weight_pounds": 210
      },
      "pts": 0,
      "reb": 0,
      "stl": 0,
      "team": {
        "id": 16,
        "abbreviation": "MIA",
        "city": "Miami",
        "conference": "East",
        "division": "Southeast",
        "full_name": "Miami Heat",
        "name": "Heat"
      },
      "turnover": 0
    },
    {
      "id": 13930863,
      "ast": 1,
      "blk": 0,
      "dreb": 0,
      "fg3_pct": 0.0,
      "fg3a": 0,
      "fg3m": 0,
      "fg_pct": 1.0,
      "fga": 2,
      "fgm": 2,
      "ft_pct": 0.0,
      "fta": 0,
      "ftm": 0,
      "game": {
        "id": 1011167,
        "date": "2023-06-07T00:00:00.000Z",
        "home_team_id": 16,
        "home_team_score": 94,
        "period": 4,
        "postseason": true,
        "season": 2022,
        "status": "Final",
        "time": "Final",
        "visitor_team_id": 8,
        "visitor_team_score": 109
      },
      "min": "17",
      "oreb": 0,
      "pf": 1,
      "player": {
        "id": 188,
        "first_name": "Jeff",
        "height_feet": 6,
        "height_inches": 9,
        "last_name": "Green",
        "position": "F",
        "team_id": 8,
        "weight_pounds": 235
      },
      "pts": 4,
      "reb": 0,
      "stl": 0,
      "team": {
        "id": 8,
        "abbreviation": "DEN",
        "city": "Denver",
        "conference": "West",
        "division": "Northwest",
        "full_name": "Denver Nuggets",
        "name": "Nuggets"
      },
      "turnover": 0
    },
    {
      "id": 13930864,
      "ast": 1,
      "blk": 0,
      "dreb": 1,
      "fg3_pct": 0.0,
      "fg3a": 1,
      "fg3m": 0,
      "fg_pct": 0.0,
      "fga": 1,
      "fgm": 0,
      "ft_pct": 0.0,
      "fta": 0,
      "ftm": 0,
      "game": {
        "id": 1011167,
        "date": "2023-06-07T00:00:00.000Z",
        "home_team_id": 16,
        "home_team_score": 94,
        "period": 4,
        "postseason": true,
        "season": 2022,
        "status": "Final",
        "time": "Final",
        "visitor_team_id": 8,
        "visitor_team_score": 109
      },
      "min": "01",
      "oreb": 0,
      "pf": 0,
      "player": {
        "id": 236,
        "first_name": "Reggie",
        "height_feet": 6,
        "height_inches": 3,
        "last_name": "Jackson",
        "position": "G",
        "team_id": 8,
        "weight_pounds": 208
      },
      "pts": 0,
      "reb": 1,
      "stl": 0,
      "team": {
        "id": 8,
        "abbreviation": "DEN",
        "city": "Denver",
        "conference": "West",
        "division": "Northwest",
        "full_name": "Denver Nuggets",
        "name": "Nuggets"
      },
      "turnover": 0
    },
    {
      "id": 13930861,
      "ast": 0,
      "blk": 0,
      "dreb": 0,
      "fg3_pct": 0.0,
      "fg3a": 0,
      "fg3m": 0,
      "fg_pct": 0.0,
      "fga": 0,
      "fgm": 0,
      "ft_pct": 0.0,
      "fta": 0,
      "ftm": 0,
      "game": {
        "id": 1011167,
        "date": "2023-06-07T00:00:00.000Z",
        "home_team_id": 16,
        "home_team_score": 94,
        "period": 4,
        "postseason": true,
        "season": 2022,
        "status": "Final",
        "time": "Final",
        "visitor_team_id": 8,
        "visitor_team_score": 109
      },
      "min": "01",
      "oreb": 0,
      "pf": 0,
      "player": {
        "id": 74,
        "first_name": "Thomas",
        "height_feet": 6,
        "height_inches": 11,
        "last_name": "Bryant",
        "position": "C",
        "team_id": 8,
        "weight_pounds": 248
      },
      "pts": 0,
      "reb": 0,
      "stl": 0,
      "team": {
        "id": 8,
        "abbreviation": "DEN",
        "city": "Denver",
        "conference": "West",
        "division": "Northwest",
        "full_name": "Denver Nuggets",
        "name": "Nuggets"
      },
      "turnover": 0
    },
    {
      "id": 13930862,
      "ast": 0,
      "blk": 0,
      "dreb": 0,
      "fg3_pct": 0.0,
      "fg3a": 0,
      "fg3m": 0,
      "fg_pct": 0.0,
      "fga": 0,
      "fgm": 0,
      "ft_pct": 0.0,
      "fta": 0,
      "ftm": 0,
      "game": {
        "id": 1011167,
        "date": "2023-06-07T00:00:00.000Z",
        "home_team_id": 16,
        "home_team_score": 94,
        "period": 4,
        "postseason": true,
        "season": 2022,
        "status": "Final",
        "time": "Final",
        "visitor_team_id": 8,
        "visitor_team_score": 109
      },
      "min": "01",
      "oreb": 0,
      "pf": 0,
      "player": {
        "id": 666489,
        "first_name": "Vlatko",
        "height_feet": null,
        "height_inches": null,
        "last_name": "Cancar",
        "position": "F",
        "team_id": 8,
        "weight_pounds": null
      },
      "pts": 0,
      "reb": 0,
      "stl": 0,
      "team": {
        "id": 8,
        "abbreviation": "DEN",
        "city": "Denver",
        "conference": "West",
        "division": "Northwest",
        "full_name": "Denver Nuggets",
        "name": "Nuggets"
      },
      "turnover": 0
    }
  ],
  "meta": {
    "total_pages": 1,
    "current_page": 1,
    "next_page": null,
    "per_page": 30,
    "total_count": 30
  }
}